cw2/__init__.py
cw2/alternative_schedulers.py
cw2/cli_parser.py
cw2/cluster_work.py
cw2/cw_error.py
cw2/default_sbatch.sh
cw2/experiment.py
cw2/job.py
cw2/scheduler.py
cw2/util.py
cw2/cw_config/__init__.py
cw2/cw_config/conf_io.py
cw2/cw_config/conf_path.py
cw2/cw_config/conf_resolver.py
cw2/cw_config/conf_unfolder.py
cw2/cw_config/cw_conf_keys.py
cw2/cw_config/cw_config.py
cw2/cw_data/__init__.py
cw2/cw_data/cw_loading.py
cw2/cw_data/cw_logging.py
cw2/cw_data/cw_pd_logger.py
cw2/cw_data/cw_wandb_logger.py
cw2/cw_slurm/__init__.py
cw2/cw_slurm/cw_slurm.py
cw2/cw_slurm/cw_slurm_keys.py
cw2-2.5.1.dist-info/LICENSE
cw2-2.5.1.dist-info/METADATA
cw2-2.5.1.dist-info/WHEEL
cw2-2.5.1.dist-info/top_level.txt
cw2-2.5.1.dist-info/RECORD
