Metadata-Version: 2.1
Name: cw2
Version: 2.5.1
Summary: A reengineered framework to run experiments on a computing cluster.
Home-page: https://github.com/ALRhub/cw2
Author: Maximilian Li
Author-email: maximilian.xiling.li@gmail.com
License: MIT
Keywords: scientific,experiments,distributed computing,mpi,research
Classifier: Development Status :: 5 - Production/Stable
Classifier: Intended Audience :: Science/Research
Classifier: Intended Audience :: Education
Classifier: Topic :: System :: Distributed Computing
Classifier: Topic :: Scientific/Engineering
Classifier: Topic :: Scientific/Engineering :: Information Analysis
Classifier: Topic :: Education
Classifier: Programming Language :: Python :: 3
Classifier: Programming Language :: Python :: 3.3
Classifier: Programming Language :: Python :: 3.4
Classifier: Programming Language :: Python :: 3.5
Classifier: Programming Language :: Python :: 3.6
Classifier: Programming Language :: Python :: 3.7
Classifier: Programming Language :: Python :: 3.8
Classifier: Programming Language :: Python :: 3.9
Classifier: Programming Language :: Python :: 3.10
Classifier: Environment :: Console
Requires-Python: >=3
License-File: LICENSE
Requires-Dist: PyYAML
Requires-Dist: numpy
Requires-Dist: pandas
Requires-Dist: joblib
